.gitignore
setup.py
docs/Makefile
docs/conf.py
docs/index.rst
docs/make.bat
docs/_themes/LICENSE
docs/_themes/README.rst
docs/_themes/flask_theme_support.py
docs/_themes/kr/layout.html
docs/_themes/kr/relations.html
docs/_themes/kr/theme.conf
docs/_themes/kr/static/flasky.css_t
docs/_themes/kr/static/small_flask.css
docs/_themes/kr_small/layout.html
docs/_themes/kr_small/theme.conf
docs/_themes/kr_small/static/flasky.css_t
indicfortune/__init__.py
indicfortune/core.py
indicfortune.egg-info/PKG-INFO
indicfortune.egg-info/SOURCES.txt
indicfortune.egg-info/dependency_links.txt
indicfortune.egg-info/not-zip-safe
indicfortune.egg-info/requires.txt
indicfortune.egg-info/top_level.txt
indicfortune/database/chanakya.dic
indicfortune/database/malayalam_proverbs.dic
indicfortune/database/thirukkural.dic
indicfortune/templates/indicfortune.html
tests/__init__.py
tests/indicfortune_test.py