Metadata-Version: 1.0
Name: indicfortune
Version: 0.2
Summary: Returns random quotes.
Home-page: UNKNOWN
Author: Santhosh Thottingal
Author-email: santhosh.thottingal@gmail.com
License: LGPL-3.0
Platform: UNKNOWN
